{
    "close": 704.0,
    "contract_type": "call_options",
    "description": "BTC  Call",
    "greeks": {
        "delta": "0.58701624",
        "gamma": "0.00025667",
        "rho": "0.16765281",
        "spot": "54311.5",
        "theta": "-1501.77658665",
        "vega": "4.90976865"
    },
    "high": 4485.0,
    "initial_margin": "1.000000000000000000",
    "low": 654.0,
    "mark_change_24h": "85.0588",
    "mark_price": "775.45212973",
    "mark_vol": "1.20340945",
    "oi": "0.0110",
    "oi_change_usd_6h": "54.2700",
    "oi_contracts": "11",
    "oi_value": "0.0110",
    "oi_value_symbol": "BTC",
    "oi_value_usd": "596.2726",
    "open": 3886.0,
    "price_band": {
        "lower_limit": "0.1",
        "upper_limit": "1853.98796489"
    },
    "product_id": 190844,
    "quotes": {
        "ask_iv": "1.22978754",
        "ask_size": "1409",
        "best_ask": "785",
        "best_bid": "759",
        "bid_iv": "1.17683109",
        "bid_size": "2114",
        "impact_mid_price": null,
        "mark_iv": "1.20348492"
    },
    "size": 153,
    "spot_price": "54317.3",
    "strike_price": "54000",
    "symbol": "C-BTC-54000-050724",
    "tags": [],
    "tick_size": "0.100000000000000000",
    "timestamp": 1720163810759246,
    "turnover": 8467.2892,
    "turnover_symbol": "USDT",
    "turnover_usd": 8467.2892,
    "underlying_asset_symbol": "BTC",
    "volume": 0.15300000000000002
}